huscy/users/__init__.py
huscy/users/apps.py
huscy/users/serializer.py
huscy/users/urls.py
huscy/users/views.py
huscy.users-1.3.0.dist-info/LICENSE
huscy.users-1.3.0.dist-info/METADATA
huscy.users-1.3.0.dist-info/WHEEL
huscy.users-1.3.0.dist-info/top_level.txt
huscy.users-1.3.0.dist-info/RECORD
