Metadata-Version: 2.1
Name: huscy.users
Version: 1.3.0
Summary: Listing and creating users via REST API
Home-page: https://bitbucket.org/huscy/users
Author: Stefan Bunde
Author-email: stefanbunde+git@posteo.de
License: AGPLv3+
Platform: UNKNOWN
Classifier: Development Status :: 5 - Production/Stable
Classifier: License :: OSI Approved :: GNU Affero General Public License v3 or later (AGPLv3+)
Classifier: Operating System :: OS Independent
Classifier: Programming Language :: Python
Classifier: Programming Language :: Python :: 3
Classifier: Programming Language :: Python :: 3 :: Only
Classifier: Programming Language :: Python :: 3.8
Classifier: Programming Language :: Python :: 3.9
Classifier: Programming Language :: Python :: 3.10
Classifier: Programming Language :: Python :: 3.11
Classifier: Framework :: Django
Classifier: Framework :: Django :: 3.2
Classifier: Framework :: Django :: 4.1
Classifier: Framework :: Django :: 4.2
Requires-Dist: Django (>=3.2)
Requires-Dist: djangorestframework (>=3.11)
Provides-Extra: development
Requires-Dist: psycopg2-binary ; extra == 'development'
Provides-Extra: testing
Requires-Dist: tox ; extra == 'testing'
Requires-Dist: watchdog ; extra == 'testing'
